{
  "syncedAt": "2026-04-15T10:45:00.7800342Z",
  "slug": "best-games-of-2008",
  "type": 1,
  "totalItems": 2,
  "data": [
    {
      "id": 530,
      "byUser": false,
      "sourceListUrl": "https://www.eurogamer.net/eurogamer-readers-top-50-games-of-2008-article",
      "dateAdded": "2023-06-14T14:24:26.921663Z",
      "dateLastUpdated": null,
      "userContributed": {
        "id": 2,
        "nickname": "diguifi",
        "fullName": "diguifi"
      },
      "source": {
        "id": 146,
        "name": "Eurogamer",
        "hostUrl": "www.eurogamer.net"
      },
      "finalGameList": {
        "id": 37,
        "title": "Best Games of",
        "year": 2008,
        "slug": "best-games-of-2008",
        "fullName": "Best Games of 2008"
      },
      "items": [
        {
          "id": 3855,
          "position": 1,
          "gameTitle": "Fallout 3",
          "gameId": 483,
          "coverImageUrl": null,
          "score": 15
        },
        {
          "id": 3856,
          "position": 2,
          "gameTitle": "Grand Theft Auto IV",
          "gameId": 337,
          "coverImageUrl": null,
          "score": 14
        },
        {
          "id": 3857,
          "position": 3,
          "gameTitle": "Gears of War 2",
          "gameId": 1146,
          "coverImageUrl": null,
          "score": 13
        },
        {
          "id": 3858,
          "position": 4,
          "gameTitle": "Metal Gear Solid 4: Guns of the Patriots",
          "gameId": 335,
          "coverImageUrl": null,
          "score": 12
        },
        {
          "id": 3859,
          "position": 5,
          "gameTitle": "LittleBigPlanet",
          "gameId": 1147,
          "coverImageUrl": null,
          "score": 11
        },
        {
          "id": 3860,
          "position": 6,
          "gameTitle": "Fable II",
          "gameId": 1148,
          "coverImageUrl": null,
          "score": 10
        },
        {
          "id": 3861,
          "position": 7,
          "gameTitle": "Left 4 Dead",
          "gameId": 1152,
          "coverImageUrl": null,
          "score": 9
        },
        {
          "id": 3862,
          "position": 8,
          "gameTitle": "Braid",
          "gameId": 630,
          "coverImageUrl": null,
          "score": 8
        },
        {
          "id": 3863,
          "position": 9,
          "gameTitle": "Burnout Paradise",
          "gameId": 1153,
          "coverImageUrl": null,
          "score": 7
        },
        {
          "id": 3864,
          "position": 10,
          "gameTitle": "Dead Space",
          "gameId": 482,
          "coverImageUrl": null,
          "score": 6
        },
        {
          "id": 3865,
          "position": 11,
          "gameTitle": "FIFA Soccer 09",
          "gameId": 1154,
          "coverImageUrl": null,
          "score": 5
        },
        {
          "id": 3866,
          "position": 12,
          "gameTitle": "Portal",
          "gameId": 508,
          "coverImageUrl": null,
          "score": 4
        },
        {
          "id": 3867,
          "position": 13,
          "gameTitle": "Rock Band 2",
          "gameId": 472,
          "coverImageUrl": null,
          "score": 3
        },
        {
          "id": 3868,
          "position": 14,
          "gameTitle": "Professor Layton and the Curious Village",
          "gameId": 1155,
          "coverImageUrl": null,
          "score": 2
        },
        {
          "id": 3869,
          "position": 15,
          "gameTitle": "Mario Kart Wii",
          "gameId": 878,
          "coverImageUrl": null,
          "score": 1
        }
      ]
    },
    {
      "id": 531,
      "byUser": false,
      "sourceListUrl": "https://www.digitalspy.com/videogames/a138960/feature-top-ten-games-of-2008/",
      "dateAdded": "2023-06-14T14:24:27.718951Z",
      "dateLastUpdated": null,
      "userContributed": {
        "id": 2,
        "nickname": "diguifi",
        "fullName": "diguifi"
      },
      "source": {
        "id": 223,
        "name": "Digitalspy",
        "hostUrl": "www.digitalspy.com"
      },
      "finalGameList": {
        "id": 37,
        "title": "Best Games of",
        "year": 2008,
        "slug": "best-games-of-2008",
        "fullName": "Best Games of 2008"
      },
      "items": [
        {
          "id": 3870,
          "position": 1,
          "gameTitle": "Grand Theft Auto IV",
          "gameId": 337,
          "coverImageUrl": null,
          "score": 15
        },
        {
          "id": 3871,
          "position": 2,
          "gameTitle": "Gears of War 2",
          "gameId": 1146,
          "coverImageUrl": null,
          "score": 14
        },
        {
          "id": 3872,
          "position": 3,
          "gameTitle": "LittleBigPlanet",
          "gameId": 1147,
          "coverImageUrl": null,
          "score": 13
        },
        {
          "id": 3873,
          "position": 4,
          "gameTitle": "Fable II",
          "gameId": 1148,
          "coverImageUrl": null,
          "score": 12
        },
        {
          "id": 3874,
          "position": 5,
          "gameTitle": "Fallout 3",
          "gameId": 483,
          "coverImageUrl": null,
          "score": 11
        },
        {
          "id": 3875,
          "position": 6,
          "gameTitle": "Far Cry 2",
          "gameId": 1149,
          "coverImageUrl": null,
          "score": 10
        },
        {
          "id": 3876,
          "position": 7,
          "gameTitle": "Call of Duty: World at War",
          "gameId": 1150,
          "coverImageUrl": null,
          "score": 9
        },
        {
          "id": 3877,
          "position": 8,
          "gameTitle": "Guitar Hero World Tour",
          "gameId": 1151,
          "coverImageUrl": null,
          "score": 8
        },
        {
          "id": 3878,
          "position": 9,
          "gameTitle": "Metal Gear Solid 4: Guns of the Patriots",
          "gameId": 335,
          "coverImageUrl": null,
          "score": 7
        },
        {
          "id": 3879,
          "position": 10,
          "gameTitle": "Braid",
          "gameId": 630,
          "coverImageUrl": null,
          "score": 6
        }
      ]
    }
  ]
}